{
"oggetti": [
{ "width": 1.24688, "height":2.09268, "name":"pippo", "img_path":"X:/Grocery stores/Grocery_products/Training//Food/Drinks/SoftDrinks/26.jpg"},
{ "width": 0.961762, "height":2.06193, "name":"pippo", "img_path":"X:/Grocery stores/Grocery_products/Training//Food/Drinks/SoftDrinks/34.jpg"},
{ "width": 0.776392, "height":1.81131, "name":"pippo", "img_path":"X:/Grocery stores/Grocery_products/Training//Food/Drinks/SoftDrinks/27.jpg"}
],
"grafo":[
{"nw":-1,"n":-1,"ne":-1,"e":2,"se":3,"s":1,"sw":13,"w":12,"ogg":0},
{"nw":12,"n":0,"ne":2,"e":3,"se":-1,"s":-1,"sw":-1,"w":13,"ogg":0},
{"nw":-1,"n":-1,"ne":-1,"e":5,"se":6,"s":3,"sw":1,"w":0,"ogg":1},
{"nw":0,"n":2,"ne":5,"e":6,"se":-1,"s":-1,"sw":-1,"w":1,"ogg":1},
{"nw":-1,"n":-1,"ne":-1,"e":12,"se":13,"s":14,"sw":-1,"w":-1,"ogg":0},
{"nw":-1,"n":-1,"ne":-1,"e":7,"se":8,"s":6,"sw":3,"w":2,"ogg":1},
{"nw":2,"n":5,"ne":10,"e":8,"se":-1,"s":-1,"sw":-1,"w":3,"ogg":1},
{"nw":-1,"n":-1,"ne":-1,"e":10,"se":9,"s":-1,"sw":-1,"w":5,"ogg":1},
{"nw":5,"n":9,"ne":11,"e":9,"se":-1,"s":-1,"sw":-1,"w":6,"ogg":1},
{"nw":7,"n":10,"ne":-1,"e":11,"se":-1,"s":8,"sw":-1,"w":8,"ogg":2},
{"nw":-1,"n":-1,"ne":-1,"e":-1,"se":11,"s":9,"sw":6,"w":7,"ogg":2},
{"nw":10,"n":-1,"ne":-1,"e":-1,"se":-1,"s":-1,"sw":8,"w":9,"ogg":2},
{"nw":-1,"n":-1,"ne":-1,"e":0,"se":1,"s":13,"sw":14,"w":4,"ogg":0},
{"nw":4,"n":12,"ne":0,"e":1,"se":-1,"s":-1,"sw":-1,"w":14,"ogg":0},
{"nw":-1,"n":4,"ne":12,"e":13,"se":-1,"s":-1,"sw":-1,"w":-1,"ogg":0}]
}
