{"objects": [{"height": 0.649869,  "width": 0.973228, "img_path": "Food/Tea/32.jpg"}, {"height": 0.934646,  "width": 0.584252, "img_path": "Food/Tea/64.jpg"}, {"height": 0.889764,  "width": 0.549606, "img_path": "Food/Tea/67.jpg"}, {"height": 0.908661,  "width": 0.567717, "img_path": "Food/Tea/70.jpg"}, {"height": 0.658268,  "width": 1.06102, "img_path": "Food/Tea/78.jpg"}, {"height": 0.810236,  "width": 0.551181, "img_path": "Food/Tea/66.jpg"}], "graph": [{"ne": 4, "nw": -1, "se": -1, "e": 5, "w": 13, "sw": -1, "s": -1, "ogg": 0, "n": 1}, {"ne": -1, "nw": -1, "se": 5, "e": 4, "w": -1, "sw": 13, "s": 0, "ogg": 0, "n": 2}, {"ne": -1, "nw": -1, "se": 4, "e": 3, "w": 14, "sw": -1, "s": 1, "ogg": 1, "n": -1}, {"ne": -1, "nw": -1, "se": -1, "e": 6, "w": 2, "sw": -1, "s": -1, "ogg": 1, "n": -1}, {"ne": 7, "nw": 2, "se": 9, "e": 8, "w": 1, "sw": 0, "s": 5, "ogg": 4, "n": -1}, {"ne": 8, "nw": 1, "se": -1, "e": 9, "w": 0, "sw": -1, "s": -1, "ogg": 4, "n": 4}, {"ne": -1, "nw": -1, "se": 8, "e": 7, "w": 3, "sw": -1, "s": -1, "ogg": 5, "n": -1}, {"ne": -1, "nw": -1, "se": -1, "e": 10, "w": 6, "sw": 4, "s": 8, "ogg": 5, "n": -1}, {"ne": 11, "nw": 6, "se": -1, "e": -1, "w": 4, "sw": 5, "s": 9, "ogg": 4, "n": 7}, {"ne": -1, "nw": 4, "se": -1, "e": -1, "w": 5, "sw": -1, "s": -1, "ogg": 4, "n": 8}, {"ne": -1, "nw": -1, "se": -1, "e": 11, "w": 7, "sw": -1, "s": -1, "ogg": 3, "n": -1}, {"ne": -1, "nw": -1, "se": -1, "e": -1, "w": 10, "sw": 8, "s": -1, "ogg": 3, "n": -1}, {"ne": -1, "nw": -1, "se": -1, "e": 14, "w": -1, "sw": -1, "s": -1, "ogg": 2, "n": -1}, {"ne": 1, "nw": -1, "se": -1, "e": 0, "w": -1, "sw": -1, "s": -1, "ogg": 0, "n": -1}, {"ne": -1, "nw": -1, "se": -1, "e": 2, "w": 12, "sw": -1, "s": -1, "ogg": 2, "n": -1}]}
