{"objects": [{"height": 0.557366,  "width": 1.01956, "img_path": "Food/Candy/Chocolate/52.jpg"}, {"height": 0.456323,  "width": 0.93807, "img_path": "Food/Candy/Chocolate/97.jpg"}, {"height": 0.499348,  "width": 0.979661, "img_path": "Food/Candy/Chocolate/109.jpg"}, {"height": 0.451543,  "width": 0.960017, "img_path": "Food/Candy/Chocolate/113.jpg"}, {"height": 0.450239,  "width": 0.964363, "img_path": "Food/Candy/Chocolate/93.jpg"}], "graph": [{"ne": 11, "nw": -1, "se": -1, "e": 15, "w": -1, "sw": -1, "s": 5, "ogg": 0, "n": -1}, {"ne": -1, "nw": -1, "se": 12, "e": 14, "w": -1, "sw": -1, "s": 2, "ogg": 0, "n": 5}, {"ne": 14, "nw": -1, "se": 13, "e": 12, "w": -1, "sw": -1, "s": 4, "ogg": 0, "n": 1}, {"ne": 13, "nw": -1, "se": -1, "e": 16, "w": -1, "sw": -1, "s": -1, "ogg": 1, "n": 4}, {"ne": 12, "nw": -1, "se": 16, "e": 13, "w": -1, "sw": -1, "s": 3, "ogg": 1, "n": 2}, {"ne": 15, "nw": -1, "se": 14, "e": -1, "w": -1, "sw": -1, "s": 1, "ogg": 0, "n": 0}, {"ne": -1, "nw": 11, "se": -1, "e": -1, "w": 15, "sw": -1, "s": 9, "ogg": 2, "n": 10}, {"ne": -1, "nw": 14, "se": -1, "e": -1, "w": 12, "sw": 13, "s": -1, "ogg": 2, "n": 8}, {"ne": -1, "nw": -1, "se": -1, "e": -1, "w": 14, "sw": 12, "s": 7, "ogg": 2, "n": 9}, {"ne": -1, "nw": 15, "se": -1, "e": -1, "w": -1, "sw": 14, "s": 8, "ogg": 2, "n": 6}, {"ne": -1, "nw": -1, "se": -1, "e": -1, "w": 11, "sw": 15, "s": 6, "ogg": 2, "n": -1}, {"ne": -1, "nw": -1, "se": 6, "e": 10, "w": -1, "sw": 0, "s": 15, "ogg": 3, "n": -1}, {"ne": 8, "nw": 1, "se": -1, "e": 7, "w": 2, "sw": 4, "s": 13, "ogg": 4, "n": 14}, {"ne": 7, "nw": 2, "se": -1, "e": -1, "w": 4, "sw": 3, "s": 16, "ogg": 4, "n": 12}, {"ne": 9, "nw": 5, "se": 7, "e": 8, "w": 1, "sw": 2, "s": 12, "ogg": 3, "n": -1}, {"ne": 10, "nw": -1, "se": 9, "e": 6, "w": 0, "sw": 5, "s": -1, "ogg": 3, "n": 11}, {"ne": -1, "nw": 4, "se": -1, "e": -1, "w": 3, "sw": -1, "s": -1, "ogg": 4, "n": 13}]}
