{"objects": [{"height": 0.382114,  "width": 1.10918, "img_path": "Food/Biscuits/6.jpg"}, {"height": 0.414634,  "width": 1.02265, "img_path": "Food/Biscuits/12.jpg"}, {"height": 0.381533,  "width": 0.951219, "img_path": "Food/Biscuits/3.jpg"}, {"height": 0.31417,  "width": 1.09582, "img_path": "Food/Biscuits/33.jpg"}, {"height": 0.324042,  "width": 0.964576, "img_path": "Food/Biscuits/24.jpg"}, {"height": 0.462834,  "width": 1.29268, "img_path": "Food/Biscuits/37.jpg"}, {"height": 0.357143,  "width": 1.1115, "img_path": "Food/Biscuits/28.jpg"}, {"height": 0.344948,  "width": 1.19454, "img_path": "Food/Biscuits/10.jpg"}], "graph": [{"ne": 13, "nw": -1, "se": -1, "e": 12, "w": -1, "sw": -1, "s": -1, "ogg": 1, "n": 2}, {"ne": 14, "nw": -1, "se": 11, "e": 10, "w": -1, "sw": -1, "s": 4, "ogg": 0, "n": 5}, {"ne": 11, "nw": -1, "se": 12, "e": 13, "w": -1, "sw": -1, "s": 0, "ogg": 1, "n": 4}, {"ne": -1, "nw": -1, "se": 14, "e": 15, "w": -1, "sw": -1, "s": 5, "ogg": 2, "n": -1}, {"ne": 10, "nw": -1, "se": 13, "e": 11, "w": -1, "sw": -1, "s": 2, "ogg": 0, "n": 1}, {"ne": 15, "nw": -1, "se": 10, "e": 14, "w": -1, "sw": -1, "s": 1, "ogg": 2, "n": 3}, {"ne": -1, "nw": 13, "se": -1, "e": -1, "w": 12, "sw": -1, "s": -1, "ogg": 4, "n": 8}, {"ne": -1, "nw": 10, "se": -1, "e": -1, "w": 11, "sw": 13, "s": 8, "ogg": 6, "n": 9}, {"ne": -1, "nw": 11, "se": -1, "e": -1, "w": 13, "sw": 12, "s": 6, "ogg": 4, "n": 7}, {"ne": -1, "nw": 14, "se": -1, "e": -1, "w": 10, "sw": 11, "s": 7, "ogg": 6, "n": -1}, {"ne": -1, "nw": 5, "se": 7, "e": 9, "w": 1, "sw": 4, "s": 11, "ogg": 7, "n": 14}, {"ne": 9, "nw": 1, "se": 8, "e": 7, "w": 4, "sw": 2, "s": 13, "ogg": 7, "n": 10}, {"ne": 8, "nw": 2, "se": -1, "e": 6, "w": 0, "sw": -1, "s": -1, "ogg": 3, "n": 13}, {"ne": 7, "nw": 4, "se": 6, "e": 8, "w": 2, "sw": 0, "s": 12, "ogg": 3, "n": 11}, {"ne": -1, "nw": 3, "se": 9, "e": -1, "w": 5, "sw": 1, "s": 10, "ogg": 5, "n": 15}, {"ne": -1, "nw": -1, "se": -1, "e": -1, "w": 3, "sw": 5, "s": 14, "ogg": 5, "n": -1}]}
